MANIFEST.in
README.rst
setup.py
facebook_wordcloud/STOPWORDS
facebook_wordcloud/__init__.py
facebook_wordcloud/arghelper.py
facebook_wordcloud/command_line.py
facebook_wordcloud/message_parser.py
facebook_wordcloud/messages_sample.htm
facebook_wordcloud/tuple_helper.py
facebook_wordcloud/word_counter.py
facebook_wordcloud.egg-info/PKG-INFO
facebook_wordcloud.egg-info/SOURCES.txt
facebook_wordcloud.egg-info/dependency_links.txt
facebook_wordcloud.egg-info/entry_points.txt
facebook_wordcloud.egg-info/not-zip-safe
facebook_wordcloud.egg-info/requires.txt
facebook_wordcloud.egg-info/top_level.txt