Metadata-Version: 1.1
Name: facebook-wordcloud
Version: 1.1
Summary: A Python tool for generating a word cloud for a Facebook chat conversation.
Home-page: https://github.com/mjmeli/facebook-chat-word-cloud
Author: Michael Meli
Author-email: facebook_wordcloud@michaelmeli.com
License: MIT
Keywords: facebook chat word cloud generate
Platform: UNKNOWN
Classifier: Development Status :: 5 - Production/Stable
Classifier: Environment :: Console
Classifier: Intended Audience :: End Users/Desktop
Classifier: License :: OSI Approved :: MIT License
Classifier: Programming Language :: Python :: 2.7
Classifier: Topic :: Multimedia :: Graphics :: Presentation
